eindex/__init__.py
eindex/_core.py
eindex/_parsing.py
eindex/array_api.py
eindex/numpy.py
eindex-0.1.0.dist-info/METADATA
eindex-0.1.0.dist-info/WHEEL
eindex-0.1.0.dist-info/RECORD
