Metadata-Version: 2.1
Name: eindex
Version: 0.1.0
Summary: A concept of multidimensional indexing for tensors
Project-URL: Homepage, https://github.com/arogozhnikov/eindex
Author: Alex Rogozhnikov
License: MIT
Keywords: eindex,einops,indexing,numpy,tensor,tensor indexing
Classifier: Intended Audience :: Science/Research
Classifier: License :: OSI Approved :: MIT License
Classifier: Programming Language :: Python :: 3
Requires-Python: >=3.8
